treespace_metrics/__init__.py
treespace_metrics/create_trees.py
treespace_metrics/drawing.py
treespace_metrics/francis.py
treespace_metrics/jetten.py
treespace_metrics/max_cst.py
treespace_metrics/utils.py
treespace_metrics-1.0.3.dist-info/licenses/LICENSE
treespace_metrics-1.0.3.dist-info/METADATA
treespace_metrics-1.0.3.dist-info/WHEEL
treespace_metrics-1.0.3.dist-info/top_level.txt
treespace_metrics-1.0.3.dist-info/RECORD
