Metadata-Version: 2.4
Name: treespace_metrics
Version: 1.0.3
Summary: Python Interface to collect treespace metrics
Home-page: https://github.com/AndrewQuijano/Treespace_REU_2017/
Author-email: Andrew Quijano <andrew.quijano@nyu.edu>
Requires-Python: >=3.8
License-File: LICENSE
Requires-Dist: networkx
Requires-Dist: matplotlib
Requires-Dist: biopython
Requires-Dist: pygraphviz
Requires-Dist: pydot
Dynamic: home-page
Dynamic: license-file
Dynamic: requires-python
